hype/__init__.py
hype/app.py
hype/color.py
hype/command.py
hype/constants.py
hype/cursor.py
hype/errors.py
hype/parser.py
hype/print.py
hype/style.py
hype/utils.py
hype/prompt/__init__.py
hype/prompt/confirm.py
hype/prompt/error.py
hype/prompt/input.py
hype/prompt/password.py
hype/prompt/getkey/__init__.py
hype/prompt/getkey/keynames.py
hype/prompt/getkey/platforms.py
hype/prompt/getkey/unikeys.py
hype/ui/__init__.py
hype/ui/constants.py
hype/ui/progress.py
hype/ui/spinner.py
hype/ui/table.py
hypecli-0.0.8.dist-info/LICENSE
hypecli-0.0.8.dist-info/METADATA
hypecli-0.0.8.dist-info/WHEEL
hypecli-0.0.8.dist-info/top_level.txt
hypecli-0.0.8.dist-info/RECORD
