Metadata-Version: 2.1
Name: hypecli
Version: 0.0.8
Summary: ⚙ A lightweight command line interface toolkit for python
Home-page: https://github.com/serumstudio/hype
Author: Serum Studio
License: MIT
Project-URL: Documentation, https://hype.serum.studio
Project-URL: Source, https://github.com/serumstudio/hype
Project-URL: Tracker, https://github.com/serumstudio/hype/issues
Keywords: cli,commandline-toolkit,command line toolkit,python cli,python 3
Platform: UNKNOWN
Classifier: Intended Audience :: Information Technology
Classifier: Intended Audience :: System Administrators
Classifier: Operating System :: OS Independent
Classifier: Programming Language :: Python :: 3
Classifier: Programming Language :: Python
Classifier: Topic :: Software Development :: Libraries :: Application Frameworks
Classifier: Topic :: Software Development :: Libraries :: Python Modules
Classifier: Topic :: Software Development :: Libraries
Classifier: Topic :: Software Development
Classifier: Typing :: Typed
Classifier: Development Status :: 4 - Beta
Classifier: Intended Audience :: Developers
Classifier: Programming Language :: Python :: 3 :: Only
Classifier: Programming Language :: Python :: 3.6
Classifier: Programming Language :: Python :: 3.7
Classifier: Programming Language :: Python :: 3.8
Classifier: License :: OSI Approved :: MIT License
License-File: LICENSE
Provides-Extra: color
Requires-Dist: colorama (==0.4.4) ; extra == 'color'
Provides-Extra: progress
Requires-Dist: alive-progress (==1.6.2) ; extra == 'progress'
Provides-Extra: standard
Requires-Dist: colorama (==0.4.4) ; extra == 'standard'
Provides-Extra: table
Requires-Dist: tabulate (==0.8.9) ; extra == 'table'
